pyscd.py
pyscd-1.0.8.dist-info/LICENSE
pyscd-1.0.8.dist-info/METADATA
pyscd-1.0.8.dist-info/WHEEL
pyscd-1.0.8.dist-info/top_level.txt
pyscd-1.0.8.dist-info/RECORD
