Metadata-Version: 2.1
Name: pyscd
Version: 1.0.8
Summary: This is a package that allows you to implement a change data capture using SCD type 2 in Pyspark
Home-page: https://github.com/Ankan1991/pyscd
Author: Ankan Mukherjee
Author-email: ankanmukherjee6@gmail.com
License: UNKNOWN
Platform: UNKNOWN
Classifier: Programming Language :: Python :: 3
Classifier: License :: OSI Approved :: Apache Software License
Classifier: Operating System :: OS Independent
Requires-Python: >=3.6
License-File: LICENSE
